{
  "جنسیت": "زن",
  "نام": "مهسا",
  "نام خانوادگی": "صادقی",
  "نام (انگلیسی)": "",
  "نام خانوادگی (انگلیسی)": "",
  "نام پدر": "",
  "ایمیل": "smah2701@gmail.com",
  "تاریخ تولد": "",
  "کد ملی": "",
  "کد پستی": "",
  "مدرک تحصیلی": "دانشجوی دکتری",
  "رشته تحصیلی": "دامپزشکی",
  "گرایش/تخصص": "",
  "موسسه/دانشگاه": "دانشگاه شهرکرد",
  "کشور": "ایران",
  "استان": "تهران",
  "شهر": "تهران",
  "تلفن همراه": 989102044365.0,
  "تلفن ثابت": "",
  "آدرس پستی": "",
  "گروه ثبت نام": "",
  "مجموع خدمات": 6000000.0,
  "مجموع پرداختی کاربر": 6000000.0,
  "مانده صورتحساب کل": 0.0,
  "تعداد مقاله": 3.0,
  "سمت": "شرکت کننده",
  "ناهار": "",
  "id": 33
}