{
  "جنسیت": "زن",
  "نام": "پریناز",
  "نام خانوادگی": "حیدری",
  "نام (انگلیسی)": "",
  "نام خانوادگی (انگلیسی)": "",
  "نام پدر": "حسن",
  "ایمیل": "heydari.parinaz99@gmail.com",
  "تاریخ تولد": "1378/01/26",
  "کد ملی": 1272893847.0,
  "کد پستی": "",
  "مدرک تحصیلی": "دانشجوی دکتری",
  "رشته تحصیلی": "دامپزشکی",
  "گرایش/تخصص": "دامپزشکی",
  "موسسه/دانشگاه": "دانشگاه آزادشهرکرد",
  "کشور": "ایران",
  "استان": "اصفهان",
  "شهر": "اصفهان",
  "تلفن همراه": 989214628992.0,
  "تلفن ثابت": 3137789487.0,
  "آدرس پستی": "",
  "گروه ثبت نام": "",
  "مجموع خدمات": 11600000.0,
  "مجموع پرداختی کاربر": 11600000.0,
  "مانده صورتحساب کل": 0.0,
  "تعداد مقاله": 0.0,
  "سمت": "شرکت کننده",
  "ناهار": "چهارشنبه و پنج شنبه",
  "id": 6
}